LICENSE
MANIFEST.in
README.rst
setup.py
django_livejs2/__init__.py
django_livejs2/middleware.py
django_livejs2.egg-info/PKG-INFO
django_livejs2.egg-info/SOURCES.txt
django_livejs2.egg-info/dependency_links.txt
django_livejs2.egg-info/top_level.txt
django_livejs2/static/django_livejs2/live.js