Metadata-Version: 1.1
Name: django-livejs2
Version: 1.0
Summary: Integrate live.js into django site
Home-page: https://github.com/SAPikachu/django-livejs2
Author: Joe Hu (SAPikachu)
Author-email: sapikachu@gmail.com
License: UNKNOWN
Platform: UNKNOWN
Classifier: Development Status :: 5 - Production/Stable
Classifier: Framework :: Django
Classifier: Intended Audience :: Developers
Classifier: License :: OSI Approved :: MIT License
Classifier: Natural Language :: English
Classifier: Programming Language :: Python :: 2.7
Classifier: Topic :: Internet :: WWW/HTTP :: WSGI :: Middleware
Classifier: Topic :: Software Development :: Libraries :: Python Modules
